masternode_health/__init__.py
masternode_health/monitor.py
masternode_health/version.py
masternode_health/test/__init__.py
masternode_health/test/test_monitor.py
masternode_health-1.0.5.dist-info/LICENSE.md
masternode_health-1.0.5.dist-info/METADATA
masternode_health-1.0.5.dist-info/WHEEL
masternode_health-1.0.5.dist-info/entry_points.txt
masternode_health-1.0.5.dist-info/top_level.txt
masternode_health-1.0.5.dist-info/RECORD
