Metadata-Version: 2.1
Name: masternode-health
Version: 1.0.5
Summary: This script is designed for collecting server & DeFiChain node information of your system and send them to the DeFiChain Masternode Health API
Home-page: http://pypi.python.org/pypi/masternode_health
Author: Christian Sandrini
Author-email: mail@chrissandrini.ch
License: LICENSE.md
Requires-Python: >2.7
License-File: LICENSE.md
Requires-Dist: psutil
Requires-Dist: requests
